[{"name":"MultiProof","step":"prove","client":"noir_rs","executionTime":130806,"peakMemoryUsage":1318993920,"meanMemoryUsage":770225519.7448692,"stdMemoryUsage":533926507.57130754,"trial":0,"treeHeight":24,"numConditions":5},{"name":"MultiProof","step":"verify","client":"noir_rs","executionTime":9165,"peakMemoryUsage":285474816,"meanMemoryUsage":238066230.5532747,"stdMemoryUsage":78201732.66112596,"trial":0,"treeHeight":24,"numConditions":5},{"name":"MultiProof","step":"prove","client":"noir_rs","executionTime":131604,"peakMemoryUsage":1301626880,"meanMemoryUsage":759569844.7666669,"stdMemoryUsage":534035248.2849326,"trial":1,"treeHeight":24,"numConditions":5},{"name":"MultiProof","step":"verify","client":"noir_rs","executionTime":9657,"peakMemoryUsage":283082752,"meanMemoryUsage":238720398.85532588,"stdMemoryUsage":76192635.01035322,"trial":1,"treeHeight":24,"numConditions":5},{"name":"MultiProof","step":"prove","client":"noir_rs","executionTime":130437,"peakMemoryUsage":1297448960,"meanMemoryUsage":765845681.7792069,"stdMemoryUsage":537097217.0826871,"trial":2,"treeHeight":24,"numConditions":5},{"name":"MultiProof","step":"verify","client":"noir_rs","executionTime":8895,"peakMemoryUsage":288718848,"meanMemoryUsage":238497332.19096774,"stdMemoryUsage":79890150.35811475,"trial":2,"treeHeight":24,"numConditions":5}]